<?xml version="1.0" encoding="UTF-8"?>
<items>
          <channel>
            <title><![CDATA[Balticum Auksinis (1)]]></title>
            <stream_url><![CDATA[http://212.12.194.10/auksinis/live.m3u8]]></stream_url>
          </channel>
        
          <channel>
            <title><![CDATA[Balticum Auksinis (2)]]></title>
            <stream_url><![CDATA[http://78.31.227.252:8080/balticumauksinis/mono.m3u8]]></stream_url>
          </channel>
        
          <channel>
            <title><![CDATA[Balticum Auksinis (3)]]></title>
            <stream_url><![CDATA[http://84.32.72.60:8080/balticum_auksinis/index.m3u8]]></stream_url>
          </channel>
        
          <channel>
            <title><![CDATA[Balticum Auksinis (4)]]></title>
            <stream_url><![CDATA[http://iptvnelt.com/kanalas/3/hls/4WT1bzMG/?type=m3u8]]></stream_url>
          </channel>
        
</items>