<?xml version="1.0" encoding="UTF-8"?>
<item>

<title><![CDATA[Duck TV]]></title>

<items>

<channel>
  <title><![CDATA[Lietuviski]]></title>
  <playlist_url><![CDATA[https://raw.githubusercontent.com/quantumducky/ducktv/master/playlists/lietuviski.m3u8]]></playlist_url>
</channel>

<channel>
  <title><![CDATA[LT-RU 1]]></title>
  <playlist_url><![CDATA[https://raw.githubusercontent.com/quantumducky/ducktv/master/playlists/lt_ru.m3u8]]></playlist_url>
</channel>

<channel>
  <title><![CDATA[LT-RU 2]]></title>
  <playlist_url><![CDATA[https://raw.githubusercontent.com/quantumducky/ducktv/master/playlists/playlist_547.m3u8]]></playlist_url>
</channel>

<channel>
  <title><![CDATA[LT-RU 3]]></title>
  <playlist_url><![CDATA[https://raw.githubusercontent.com/quantumducky/ducktv/master/playlists/Playlist_With_LT.m3u]]></playlist_url>
</channel>

<channel>
  <title><![CDATA[LT]]></title>
  <playlist_url><![CDATA[https://raw.githubusercontent.com/quantumducky/ducktv/master/playlists/Playlist_LT.m3u]]></playlist_url>
</channel>

<channel>
  <title><![CDATA[Edem (LT-RU)]]></title>
  <playlist_url><![CDATA[https://raw.githubusercontent.com/quantumducky/ducktv/master/playlists/edem12_26.m3u8]]></playlist_url>
</channel>

<channel>
  <title><![CDATA[Ott Club (LT-RU)]]></title>
  <playlist_url><![CDATA[https://raw.githubusercontent.com/quantumducky/ducktv/master/playlists/ott_club.m3u8]]></playlist_url>
</channel>

<channel>
  <title><![CDATA[Во все тяжкие]]></title>
  <playlist_url><![CDATA[https://raw.githubusercontent.com/quantumducky/ducktv/master/playlists/bb.m3u8]]></playlist_url>
</channel>

<channel>
  <title><![CDATA[Во все тяжкие]]></title>
  <playlist_url><![CDATA[https://raw.githubusercontent.com/quantumducky/ducktv/master/test.m3u8]]></playlist_url>
</channel>

</items></item>