<?xml version="1.0" encoding="UTF-8"?>
<items>
    <channel>
      <title><![CDATA[0-9]]></title>
      <playlist_url><![CDATA[https://raw.githubusercontent.com/quantumducky/ducktv/master/movies/years/0-9.xml]]></playlist_url>
    </channel>
    
    <channel>
      <title><![CDATA[A]]></title>
      <playlist_url><![CDATA[https://raw.githubusercontent.com/quantumducky/ducktv/master/movies/years/A.xml]]></playlist_url>
    </channel>
    
    <channel>
      <title><![CDATA[B]]></title>
      <playlist_url><![CDATA[https://raw.githubusercontent.com/quantumducky/ducktv/master/movies/years/B.xml]]></playlist_url>
    </channel>
    
    <channel>
      <title><![CDATA[C]]></title>
      <playlist_url><![CDATA[https://raw.githubusercontent.com/quantumducky/ducktv/master/movies/years/C.xml]]></playlist_url>
    </channel>
    
    <channel>
      <title><![CDATA[Č]]></title>
      <playlist_url><![CDATA[https://raw.githubusercontent.com/quantumducky/ducktv/master/movies/years/Č.xml]]></playlist_url>
    </channel>
    
    <channel>
      <title><![CDATA[D]]></title>
      <playlist_url><![CDATA[https://raw.githubusercontent.com/quantumducky/ducktv/master/movies/years/D.xml]]></playlist_url>
    </channel>
    
    <channel>
      <title><![CDATA[E]]></title>
      <playlist_url><![CDATA[https://raw.githubusercontent.com/quantumducky/ducktv/master/movies/years/E.xml]]></playlist_url>
    </channel>
    
    <channel>
      <title><![CDATA[F]]></title>
      <playlist_url><![CDATA[https://raw.githubusercontent.com/quantumducky/ducktv/master/movies/years/F.xml]]></playlist_url>
    </channel>
    
    <channel>
      <title><![CDATA[G]]></title>
      <playlist_url><![CDATA[https://raw.githubusercontent.com/quantumducky/ducktv/master/movies/years/G.xml]]></playlist_url>
    </channel>
    
    <channel>
      <title><![CDATA[H]]></title>
      <playlist_url><![CDATA[https://raw.githubusercontent.com/quantumducky/ducktv/master/movies/years/H.xml]]></playlist_url>
    </channel>
    
    <channel>
      <title><![CDATA[I]]></title>
      <playlist_url><![CDATA[https://raw.githubusercontent.com/quantumducky/ducktv/master/movies/years/I.xml]]></playlist_url>
    </channel>
    
    <channel>
      <title><![CDATA[Į]]></title>
      <playlist_url><![CDATA[https://raw.githubusercontent.com/quantumducky/ducktv/master/movies/years/Į.xml]]></playlist_url>
    </channel>
    
    <channel>
      <title><![CDATA[J]]></title>
      <playlist_url><![CDATA[https://raw.githubusercontent.com/quantumducky/ducktv/master/movies/years/J.xml]]></playlist_url>
    </channel>
    
    <channel>
      <title><![CDATA[K]]></title>
      <playlist_url><![CDATA[https://raw.githubusercontent.com/quantumducky/ducktv/master/movies/years/K.xml]]></playlist_url>
    </channel>
    
    <channel>
      <title><![CDATA[L]]></title>
      <playlist_url><![CDATA[https://raw.githubusercontent.com/quantumducky/ducktv/master/movies/years/L.xml]]></playlist_url>
    </channel>
    
    <channel>
      <title><![CDATA[M]]></title>
      <playlist_url><![CDATA[https://raw.githubusercontent.com/quantumducky/ducktv/master/movies/years/M.xml]]></playlist_url>
    </channel>
    
    <channel>
      <title><![CDATA[N]]></title>
      <playlist_url><![CDATA[https://raw.githubusercontent.com/quantumducky/ducktv/master/movies/years/N.xml]]></playlist_url>
    </channel>
    
    <channel>
      <title><![CDATA[O]]></title>
      <playlist_url><![CDATA[https://raw.githubusercontent.com/quantumducky/ducktv/master/movies/years/O.xml]]></playlist_url>
    </channel>
    
    <channel>
      <title><![CDATA[P]]></title>
      <playlist_url><![CDATA[https://raw.githubusercontent.com/quantumducky/ducktv/master/movies/years/P.xml]]></playlist_url>
    </channel>
    
    <channel>
      <title><![CDATA[Q]]></title>
      <playlist_url><![CDATA[https://raw.githubusercontent.com/quantumducky/ducktv/master/movies/years/Q.xml]]></playlist_url>
    </channel>
    
    <channel>
      <title><![CDATA[R]]></title>
      <playlist_url><![CDATA[https://raw.githubusercontent.com/quantumducky/ducktv/master/movies/years/R.xml]]></playlist_url>
    </channel>
    
    <channel>
      <title><![CDATA[S]]></title>
      <playlist_url><![CDATA[https://raw.githubusercontent.com/quantumducky/ducktv/master/movies/years/S.xml]]></playlist_url>
    </channel>
    
    <channel>
      <title><![CDATA[Š]]></title>
      <playlist_url><![CDATA[https://raw.githubusercontent.com/quantumducky/ducktv/master/movies/years/Š.xml]]></playlist_url>
    </channel>
    
    <channel>
      <title><![CDATA[T]]></title>
      <playlist_url><![CDATA[https://raw.githubusercontent.com/quantumducky/ducktv/master/movies/years/T.xml]]></playlist_url>
    </channel>
    
    <channel>
      <title><![CDATA[U]]></title>
      <playlist_url><![CDATA[https://raw.githubusercontent.com/quantumducky/ducktv/master/movies/years/U.xml]]></playlist_url>
    </channel>
    
    <channel>
      <title><![CDATA[Ū]]></title>
      <playlist_url><![CDATA[https://raw.githubusercontent.com/quantumducky/ducktv/master/movies/years/Ū.xml]]></playlist_url>
    </channel>
    
    <channel>
      <title><![CDATA[V]]></title>
      <playlist_url><![CDATA[https://raw.githubusercontent.com/quantumducky/ducktv/master/movies/years/V.xml]]></playlist_url>
    </channel>
    
    <channel>
      <title><![CDATA[W]]></title>
      <playlist_url><![CDATA[https://raw.githubusercontent.com/quantumducky/ducktv/master/movies/years/W.xml]]></playlist_url>
    </channel>
    
    <channel>
      <title><![CDATA[X]]></title>
      <playlist_url><![CDATA[https://raw.githubusercontent.com/quantumducky/ducktv/master/movies/years/X.xml]]></playlist_url>
    </channel>
    
    <channel>
      <title><![CDATA[Y]]></title>
      <playlist_url><![CDATA[https://raw.githubusercontent.com/quantumducky/ducktv/master/movies/years/Y.xml]]></playlist_url>
    </channel>
    
    <channel>
      <title><![CDATA[Z]]></title>
      <playlist_url><![CDATA[https://raw.githubusercontent.com/quantumducky/ducktv/master/movies/years/Z.xml]]></playlist_url>
    </channel>
    
    <channel>
      <title><![CDATA[Ž]]></title>
      <playlist_url><![CDATA[https://raw.githubusercontent.com/quantumducky/ducktv/master/movies/years/Ž.xml]]></playlist_url>
    </channel>
    
    <channel>
      <title><![CDATA[А]]></title>
      <playlist_url><![CDATA[https://raw.githubusercontent.com/quantumducky/ducktv/master/movies/years/А.xml]]></playlist_url>
    </channel>
    
    <channel>
      <title><![CDATA[П]]></title>
      <playlist_url><![CDATA[https://raw.githubusercontent.com/quantumducky/ducktv/master/movies/years/П.xml]]></playlist_url>
    </channel>
    
</items>